{
	"user"				: "seolim",
	"userDescription"	: "anything do",
	"blogTitle"			: "seolim`s blog",
	"blogDescription"	: "doing anything",
	"lastPosts"			: [
		["React", "Acknownledge", "Redux 2"],
		["React", "Acknownledge", "Redux 1"],
		["React", "Acknownledge", "babel"],
		["React", "Acknownledge", "WebPack"],
		["React", "Blog Project", "React Blog"]
	],
	"POSTS"				: [
		{
			"groupName" : "42Project",
			"categories" : [
				{
					"categoryName"	: "miniShell",
					"posts"			: [
						
					]
				}
			]
		},
		{
			"groupName" : "React",
			"categories" : [
				{
					"categoryName"	: "Acknownledge",
					"posts"			: [
						{
							"groupName"		: "React",
							"categoryName"	: "Acknownledge",
							"title" 		: "WebPack",
							"author"		: "seolim",
							"date"			: "2020-05-22",
							"preview"		: "What is Webpack"
						},
						{
							"groupName"		: "React",
							"categoryName"	: "Acknownledge",
							"title" 		: "babel",
							"author"		: "seolim",
							"date"			: "2020-05-23",
							"preview"		: "What is babel"
						},
						{
							"groupName"		: "React",
							"categoryName"	: "Acknownledge",
							"title" 		: "Redux 1",
							"author"		: "seolim",
							"date"			: "2020-05-25",
							"preview"		: "What is Redux"
						},
						{
							"groupName"		: "React",
							"categoryName"	: "Acknownledge",
							"title" 		: "Redux 2",
							"author"		: "seolim",
							"date"			: "2020-05-25",
							"preview"		: "What is Redux"
						}
					]
				},
				{
					"categoryName"	: "Blog Project",
					"posts"			: [
						{
							"groupName"		: "React",
							"categoryName"	: "Blog Project",
							"title" 		: "React Blog",
							"author"		: "seolim",
							"date"			: "2020-05-21",
							"preview"		: "react blot start project"
						},
						{
							"groupName"		: "React",
							"categoryName"	: "Blog Project",
							"title" 		: "Redux Router",
							"author"		: "seolim",
							"date"			: "2020-05-22",
							"preview"		: "Redux and Router Setting"
						}
					]
				}
			]
		}
	]
}